[{"id":"1","name":"rifleman","cost":3000,"actionid":2,"gEDefaultUniformTemplateId":"21","uSDefaultUniformTemplateId":"23","rUDefaultUniformTemplateId":"28","equipmentPoints":10,"deployPoolCost":10,"deployPoolSwitchCost":0,"deployPoolOffClassCost":50},{"id":"2","name":"fighterpilot","cost":7975,"actionid":11,"gEDefaultUniformTemplateId":"22","uSDefaultUniformTemplateId":"25","rUDefaultUniformTemplateId":"32","equipmentPoints":6,"deployPoolCost":100,"deployPoolSwitchCost":0,"deployPoolOffClassCost":300},{"id":"4","name":"paratrooper","cost":6425,"actionid":7,"gEDefaultUniformTemplateId":"5","uSDefaultUniformTemplateId":"14","rUDefaultUniformTemplateId":"30","equipmentPoints":8,"deployPoolCost":28,"deployPoolSwitchCost":0,"deployPoolOffClassCost":200},{"id":"5","name":"tankcrew","cost":7725,"actionid":10,"gEDefaultUniformTemplateId":"1","uSDefaultUniformTemplateId":"24","rUDefaultUniformTemplateId":"29","equipmentPoints":6,"deployPoolCost":100,"deployPoolSwitchCost":0,"deployPoolOffClassCost":300},{"id":"6","name":"recon","cost":8325,"actionid":6,"gEDefaultUniformTemplateId":"10","uSDefaultUniformTemplateId":"18","rUDefaultUniformTemplateId":"31","equipmentPoints":8,"deployPoolCost":60,"deployPoolSwitchCost":0,"deployPoolOffClassCost":200},{"id":"7","name":"general","cost":0,"actionid":7,"gEDefaultUniformTemplateId":"26","uSDefaultUniformTemplateId":"27","rUDefaultUniformTemplateId":"132","equipmentPoints":0,"deployPoolCost":0,"deployPoolSwitchCost":0,"deployPoolOffClassCost":0}]